{
	"additionalNodes": [],
	"additionalParameters": {
		"root": {
			"height": 88,
			"width": 180
		}
	},
	"inputs": [],
	"outputs": [],
	"properties": {
		"xypVnSNrTkh34WnVYx3uS2OKCYqPW82h": {
			"height": 92,
			"title": "store",
			"width": 129,
			"x": 255,
			"y": -14
		}
	},
	"roles": [ {
		"categories": [],
		"name": "Role 1"
	} ],
	"root": {
		"children": [],
		"id": "xypVnSNrTkh34WnVYx3uS2OKCYqPW82h",
		"nodeType": "luaCommand",
		"parameters": [ {
			"name": "var",
			"value": "Common"
		}, {
			"name": "value",
			"value": "1"
		}, {
			"name": "scriptName",
			"value": "store"
		} ],
		"scriptName": "store"
	}
}